setup.py
printind/__init__.py
printind/printind_decorators.py
printind/printind_function.py
printind.egg-info/PKG-INFO
printind.egg-info/SOURCES.txt
printind.egg-info/dependency_links.txt
printind.egg-info/top_level.txt