Metadata-Version: 1.0
Name: printind
Version: 4.0
Summary: Print function indented by the calling function stack depth using the traceback module
Home-page: https://github.com/jerabaul29/python_printind
Author: jerabaul29
Author-email: jean.rblt@gmail.com
License: MIT
Platform: UNKNOWN
